igrins_instruments/__init__.py
igrins_instruments/igrins/__init__.py
igrins_instruments/igrins/adclass.py
igrins_instruments/igrins/lookup.py
igrins_instruments/igrins/tests/__init__.py
igrins_instruments/igrins/tests/preprare_test_header.py
igrins_instruments/igrins/tests/raw_data/N20251106S0434_H.fits
igrins_instruments/igrins/tests/test_ad.py
igrins_instruments/igrins/tests/test_data/__init__.py
igrins_instruments/igrins/tests/test_data/sample_flatoff/N20240429S0365_H.fits
igrins_instruments/igrins/tests/test_data/sample_flatoff/N20240721S0276_H.fits
igrins_instruments/igrins/tests/test_data/sample_flaton/N20240429S0375_H.fits
igrins_instruments/igrins/tests/test_data/sample_flaton/N20240721S0295_H.fits
igrins_instruments/igrins/tests/test_data/sample_flaton/N20251106S0434_H.fits
igrins_instruments/igrins/tests/test_data/sample_mef/N20240429S0122.fits
igrins_instruments/igrins/tests/test_data/sample_mef/N20240429S0125.fits
igrins_instruments/igrins/tests/test_data/sample_mef/N20240429S0204.fits
igrins_instruments/igrins/tests/test_data/sample_mef/N20240429S0365.fits
igrins_instruments/igrins/tests/test_data/sample_mef/N20240429S0375.fits
igrins_instruments/igrins/tests/test_data/sample_sky/N20240429S0204_H.fits
igrins_instruments/igrins/tests/test_data/sample_sky/N20240721S0132_H.fits
igrins_instruments/igrins/tests/test_data/sample_std/N20240429S0125_H.fits
igrins_instruments/igrins/tests/test_data/sample_std/N20240721S0128_H.fits
igrins_instruments/igrins/tests/test_data/sample_tgt/N20240429S0122_H.fits
igrins_instruments/igrins/tests/test_data/sample_tgt/N20240721S0116_H.fits
igrins_instruments/igrins/tests/test_flaton.py
igrins_instruments/igrins/tests/test_utdate.py
igrinsdr/__init__.py
igrinsdr/_version.py
igrinsdr/doc/usermanuals/IGRINSDR_UserManual/README
igrinsdr/igrins/__init__.py
igrinsdr/igrins/json_helper.py
igrinsdr/igrins/lookups/BPM/README
igrinsdr/igrins/lookups/MDF/README
igrinsdr/igrins/lookups/__init__.py
igrinsdr-0.1.2.dist-info/METADATA
igrinsdr-0.1.2.dist-info/WHEEL
igrinsdr-0.1.2.dist-info/licenses/LICENSE
igrinsdr-0.1.2.dist-info/RECORD
